{
    "list": [
        {
            "repertory": 200,
            "allsales": 2000,
            "name": "钻先生GIA裸钻2克拉1克拉钻石戒指正品一克拉钻戒定制3克拉婚戒女",
            "imgUrl": "https://gd3.alicdn.com/imgextra/i1/2126094071/TB2UOi6ksLJ8KJjy0FnXXcFDpXa_!!2126094071.jpg",
            "price": 1390000,
            "sale": 100000,
            "detailimageOne": "https://img.alicdn.com/tps/i1/TB1AHXiGXXXXXXAXVXX.uTD.FXX-10-10.png",
            "detailimageTwo": "https://img.alicdn.com/tps/i1/TB1AHXiGXXXXXXAXVXX.uTD.FXX-10-10.png",
            "detailimageThree": "https://img30.360buyimg.com/popWaterMark/jfs/t21292/283/697906787/176274/c7d9a36c/5b15f14cN348aef8f.jpg"
        },
        {
            "repertory": 200,
            "allsales": 3000,
            "name": "瓦萨比 千层塔火焰聚宝盆白幽灵水晶手链男女首饰品珠宝配饰",
            "imgUrl": "https://gd3.alicdn.com/imgextra/i3/33507876/TB2YEwIXtFopuFjSZFHXXbSlXXa_!!33507876.jpg",
            "price": 239,
            "sale": 200,
            "detailimageOne": "https://img.alicdn.com/imgextra/i3/33507876/TB2hLfWjbBnpuFjSZFGXXX51pXa_!!33507876.jpg",
            "detailimageTwo": "https://img.alicdn.com/imgextra/i3/33507876/TB2z2wCjbBmpuFjSZFAXXaQ0pXa_!!33507876.jpg",
            "detailimageThree": "https://img.alicdn.com/tps/i1/TB1AHXiGXXXXXXAXVXX.uTD.FXX-10-10.png"
        },
        {
            "repertory": 600,
            "allsales": 1500,
            "name": "远洋工坊 汉服配饰青金石烧蓝多宝项链璎珞(接受定制）",
            "imgUrl": "https://gd3.alicdn.com/imgextra/i1/2116212139/TB23TuQlVXXXXakXXXXXXXXXXXX_!!2116212139.jpg",
            "price": 223,
            "sale": 199,
            "detailimageOne": "https://img.alicdn.com/imgextra/i3/2116212139/TB2vuGUlVXXXXX_XXXXXXXXXXXX_!!2116212139.jpg",
            "detailimageTwo": "https://img.alicdn.com/imgextra/i4/2116212139/TB2eVewlVXXXXc5XXXXXXXXXXXX_!!2116212139.jpg",
            "detailimageThree": "https://img.alicdn.com/imgextra/i3/2116212139/TB2FhuClVXXXXcrXXXXXXXXXXXX_!!2116212139.jpg"

        },
        {
            "repertory": 760,
            "allsales": 4210,
            "name": "易行堂星月菩提配饰套餐私人定制蜜蜡南红青金石顶珠腰珠三通佛头",
            "imgUrl": "https://img.alicdn.com/imgextra/i1/2422222119/TB2DurcdzQnBKNjSZSgXXXHGXXa_!!2422222119.jpg_60x60q90.jpg",
            "price": 199,
            "sale": 149,
            "detailimageOne": "https://img.alicdn.com/imgextra/i3/2422222119/TB2l5pmX3KTBuNkSne1XXaJoXXa_!!2422222119.jpg",
            "detailimageTwo": "https://img.alicdn.com/imgextra/i1/2422222119/TB2THY7boR1BeNjy0FmXXb0wVXa_!!2422222119.jpg",
            "detailimageThree": "https://img.alicdn.com/imgextra/i4/2422222119/TB2HiXiX5CYBuNkSnaVXXcMsVXa_!!2422222119.jpg"

        },
        {
            "repertory": 900,
            "allsales": 500,
            "name": "日本定制18k白金钻石配akoya日本海水珍珠音符耳钉",
            "imgUrl": "https://gd2.alicdn.com/imgextra/i3/592885971/TB2Jg8RaS3PL1JjSZFxXXcBBVXa_!!592885971.jpg",
            "price": 3249,
            "sale": 999,
            "detailimageOne": "https://img.alicdn.com/imgextra/i3/592885971/TB2Cdt1aUEIL1JjSZFFXXc5kVXa_!!592885971.jpg",
            "detailimageTwo": "https://img.alicdn.com/imgextra/i1/592885971/TB2VPB7aPoIL1JjSZFyXXbFBpXa_!!592885971.jpg",
            "detailimageThree": "https://img.alicdn.com/imgextra/i2/592885971/TB2SpJ2aRoHL1JjSZFwXXb6vpXa_!!592885971.jpg"

        },
        {
            "repertory": 560,
            "allsales": 2880,
            "name": "悦宝家天然多米尼加海纹石吊坠18K金项链钻石镶嵌私人定制礼物",
            "imgUrl": "https://gd1.alicdn.com/imgextra/i3/108323362/TB2MElotrSYBuNjSspiXXXNzpXa_!!108323362.jpg",
            "price": 3290,
            "sale": 1830,
            "detailimageOne": "https://img.alicdn.com/imgextra/i2/108323362/TB2eQacbXuWBuNjSspnXXX1NVXa_!!108323362.jpg",
            "detailimageTwo": "https://img.alicdn.com/imgextra/i4/108323362/TB2Mbuhbb1YBuNjSszhXXcUsFXa_!!108323362.jpg",
            "detailimageThree": "https://img.alicdn.com/imgextra/i2/108323362/TB2pqShbkSWBuNjSszdXXbeSpXa_!!108323362.jpg"
        },
        {
            "repertory": 500,
            "allsales": 2500,
            "name": "kkdiamond GIA证书订制公主方钻石1.01克拉 F VS1 18k白金项链",
            "imgUrl": "https://gd1.alicdn.com/imgextra/i1/919601575/TB2segtasaK.eBjSspjXXXL.XXa_!!919601575.jpg",
            "price": 33400,
            "sale": 30000,
            "detailimageOne": "https://img.alicdn.com/imgextra/i2/919601575/TB2ut6KaQ1M.eBjSZFFXXc3vVXa_!!919601575.jpg",
            "detailimageTwo": "https://img.alicdn.com/imgextra/i2/919601575/TB2IKbOaF5N.eBjSZFKXXX_QVXa_!!919601575.jpg",
            "detailimageThree": "https://img.alicdn.com/imgextra/i3/919601575/TB2OxgjareI.eBjSspkXXaXqVXa_!!919601575.jpg"
        },
        {
            "repertory": 334,
            "allsales": 1000,
            "name": "【定制】即刻寻宝 琳达 Linda 意大利贝雕美人手链给自己礼物",
            "imgUrl": "https://gd2.alicdn.com/imgextra/i2/0/TB1kFNMhsjI8KJjSsppXXXbyVXa_!!0-item_pic.jpg",
            "price": 139,
            "sale": 99,
            "detailimageOne": "https://img.alicdn.com/imgextra/i1/3341208631/TB2xzFHcLjM8KJjSZFNXXbQjFXa_!!3341208631.jpg",
            "detailimageTwo": "https://img.alicdn.com/imgextra/i4/3341208631/TB2wt0xcMjN8KJjSZFgXXbjbVXa_!!3341208631.jpg",
            "detailimageThree": "https://img.alicdn.com/imgextra/i1/3341208631/TB2prdGcJLO8KJjSZFxXXaGEVXa_!!3341208631.jpg"
        },
        {
            "repertory": 800,
            "allsales": 2000,
            "name": "韩国东大门甜美小猫咪花朵钟表多元素四叶草串珠手链手串手饰品女",
            "imgUrl": "https://gd2.alicdn.com/imgextra/i3/3004028134/TB2PEdhhLiSBuNkSnhJXXbDcpXa_!!3004028134.jpg",
            "price": 539,
            "sale": 99,
            "detailimageOne": "https://img.alicdn.com/imgextra/i2/3004028134/TB23cP0tHSYBuNjSspfXXcZCpXa_!!3004028134.jpg",
            "detailimageTwo": "https://img.alicdn.com/imgextra/i3/3004028134/TB2PEdhhLiSBuNkSnhJXXbDcpXa_!!3004028134.jpg",
            "detailimageThree": "https://img.alicdn.com/imgextra/i2/3004028134/TB28YGqpVGWBuNjy0FbXXb4sXXa_!!3004028134.jpg"
        },
        {
            "repertory": 680,
            "allsales": 2600,
            "name": "T公馆 独立高段位定制 巴洛克荧光绿珍珠满钻短颈装饰项链",
            "imgUrl": "https://gd1.alicdn.com/imgextra/i3/0/T1ZNeDFNhbXXXXXXXX_!!0-item_pic.jpg",
            "price": 188,
            "sale": 168,
            "detailimageOne": "https://img.alicdn.com/imgextra/i1/313797710/T2spbRXsBXXXXXXXXX_!!313797710.jpg",
            "detailimageTwo": "https://img.alicdn.com/imgextra/i1/313797710/T2a4TCXSdXXXXXXXXX-313797710.jpg",
            "detailimageThree": "https://img.alicdn.com/imgextra/i1/313797710/T2a4TCXSdXXXXXXXXX-313797710.jpg"
        },
        {
            "repertory": 600,
            "allsales": 1800,
            "name": "Alice爱丽丝珠宝 欧泊吊坠18K金镶嵌天然彩宝锁骨项链女 星空系列",
            "imgUrl": "https://img.alicdn.com/imgextra/i4/3064496109/TB1wZ5KwAOWBuNjSsppXXXPgpXa_!!0-item_pic.jpg_60x60q90.jpg",
            "price": 199,
            "sale": 159,
            "detailimageOne": "https://img.alicdn.com/imgextra/i4/3064496109/TB2ysTBweySBuNjy1zdXXXPxFXa_!!3064496109.jpg",
            "detailimageTwo": "https://img.alicdn.com/imgextra/i4/3064496109/TB2ysTBweySBuNjy1zdXXXPxFXa_!!3064496109.jpg",
            "detailimageThree": "https://img.alicdn.com/imgextra/i4/3064496109/TB2XWHiwb1YBuNjSszeXXablFXa_!!3064496109.jpg"

        },
        {
            "repertory": 500,
            "allsales": 900,
            "name": "复古民族风女长款毛衣链子木质吊坠挂件文艺百搭配饰品挂坠",
            "imgUrl": "https://gd2.alicdn.com/imgextra/i2/2744918846/TB2KupygvImBKNjSZFlXXc43FXa_!!2744918846.jpg",
            "price": 239,
            "sale": 199,
            "detailimageOne": "https://img.alicdn.com/imgextra/i3/2744918846/TB2sVMIsH1YBuNjSszhXXcUsFXa_!!2744918846.jpg",
            "detailimageTwo": "https://img.alicdn.com/imgextra/i3/2744918846/TB2Y9CAs_tYBeNjy1XdXXXXyVXa_!!2744918846.jpg",
            "detailimageThree": "https://img.alicdn.com/imgextra/i2/2744918846/TB2Hz_ZsL9TBuNjy0FcXXbeiFXa_!!2744918846.jpg"

        },
        {
            "repertory": 300,
            "allsales": 500,
            "name": "简约大气水晶花朵吊坠流苏毛衣链百搭长款挂链春夏裙配饰项链饰品",
            "imgUrl": "https://gd4.alicdn.com/imgextra/i2/380152824/TB2.tfYnXXXXXXpXXXXXXXXXXXX_!!380152824.jpg",
            "price": 219,
            "sale": 199,
            "detailimageOne": "https://img.alicdn.com/imgextra/i1/380152824/TB2.jg1cBLN8KJjSZPhXXc.spXa_!!380152824.jpg",
            "detailimageTwo": "https://img.alicdn.com/imgextra/i1/380152824/TB2.jg1cBLN8KJjSZPhXXc.spXa_!!380152824.jpg",
            "detailimageThree": "https://img.alicdn.com/imgextra/i2/380152824/TB2RskDidbJ8KJjy1zjXXaqapXa_!!380152824.jpg"

        },
        {
            "repertory": 400,
            "allsales": 9000,
            "name": "民族风 百搭朱砂红配饰女百搭挂饰挂链秋冬 毛衣链长款",
            "imgUrl": "https://gd2.alicdn.com/imgextra/i4/2994280961/TB2GJ4shEOWBKNjSZKzXXXfWFXa_!!2994280961.jpg",
            "price": 139,
            "sale": 89,
            "detailimageOne": "https://img.alicdn.com/imgextra/i4/2994280961/TB2NS4jboD.BuNjt_h7XXaNDVXa_!!2994280961.jpg",
            "detailimageTwo": "https://img.alicdn.com/imgextra/i2/2994280961/TB2N.evvv5TBuNjSspcXXbnGFXa_!!2994280961.jpg",
            "detailimageThree": "https://img.alicdn.com/imgextra/i4/2994280961/TB2RQmTvx1YBuNjy1zcXXbNcXXa_!!2994280961.jpg"
        },
        {
            "repertory": 800,
            "allsales": 1420,
            "name": "采用施华洛世奇元素水晶戒指男女 日韩简约食指戒方块对戒配饰品",
            "imgUrl": "https://gd2.alicdn.com/imgextra/i1/0/TB1Av.BeuSSBuNjy0FlXXbBpVXa_!!0-item_pic.jpg",
            "price": 89,
            "sale": 69,
            "detailimageOne": "https://img.alicdn.com/imgextra/i1/3457857640/TB2zHocewmTBuNjy1XbXXaMrVXa_!!3457857640.jpg",
            "detailimageTwo": "https://img.alicdn.com/imgextra/i1/3457857640/TB2zHocewmTBuNjy1XbXXaMrVXa_!!3457857640.jpg",
            "detailimageThree": "https://img.alicdn.com/imgextra/i1/3457857640/TB2zHocewmTBuNjy1XbXXaMrVXa_!!3457857640.jpg"
        }
    ]
}